realmaths/__init__.py
realmaths/cli.py
realmaths/core.py
realmaths/examples.py
realmaths/exceptions.py
realmaths-1.0.3.dist-info/METADATA
realmaths-1.0.3.dist-info/WHEEL
realmaths-1.0.3.dist-info/entry_points.txt
realmaths-1.0.3.dist-info/top_level.txt
realmaths-1.0.3.dist-info/RECORD
