Metadata-Version: 2.4
Name: realmaths
Version: 1.0.3
Summary: Natural mathematical expressions for non-programmers
Home-page: https://github.com/conorzen/realmaths
Author: Conor Reid
Author-email: Your Name <your.email@example.com>
Maintainer-email: Your Name <your.email@example.com>
Project-URL: Homepage, https://github.com/conorzen/realmaths
Project-URL: Documentation, https://github.com/conorzen/realmaths#readme
Project-URL: Repository, https://github.com/conorzen/realmaths.git
Project-URL: Bug Tracker, https://github.com/conorzen/realmaths/issues
Project-URL: Changelog, https://github.com/conorzen/realmaths/blob/main/CHANGELOG.md
Project-URL: Source Code, https://github.com/conorzen/realmaths
Keywords: mathematics,calculator,expressions,education,natural-language,non-programmer,math-notation,student-friendly
Classifier: Development Status :: 4 - Beta
Classifier: Intended Audience :: Education
Classifier: Intended Audience :: Science/Research
Classifier: Topic :: Scientific/Engineering :: Mathematics
Classifier: Topic :: Education
Classifier: License :: OSI Approved :: MIT License
Classifier: Programming Language :: Python :: 3
Classifier: Programming Language :: Python :: 3.8
Classifier: Programming Language :: Python :: 3.9
Classifier: Programming Language :: Python :: 3.10
Classifier: Programming Language :: Python :: 3.11
Classifier: Programming Language :: Python :: 3.12
Classifier: Operating System :: OS Independent
Classifier: Natural Language :: English
Requires-Python: >=3.7
Provides-Extra: dev
Requires-Dist: pytest>=7.0.0; extra == "dev"
Requires-Dist: pytest-cov>=4.0.0; extra == "dev"
Requires-Dist: black>=22.0.0; extra == "dev"
Requires-Dist: flake8>=6.0.0; extra == "dev"
Requires-Dist: mypy>=1.0.0; extra == "dev"
Requires-Dist: isort>=5.10.0; extra == "dev"
Requires-Dist: pre-commit>=2.20.0; extra == "dev"
Provides-Extra: docs
Requires-Dist: sphinx>=6.0.0; extra == "docs"
Requires-Dist: sphinx-rtd-theme>=1.0.0; extra == "docs"
Requires-Dist: myst-parser>=2.0.0; extra == "docs"
Provides-Extra: test
Requires-Dist: pytest>=7.0.0; extra == "test"
Requires-Dist: pytest-cov>=4.0.0; extra == "test"
Requires-Dist: pytest-xdist>=3.0.0; extra == "test"
Requires-Dist: hypothesis>=6.0.0; extra == "test"
Provides-Extra: full
Requires-Dist: realmaths[dev,docs,test]; extra == "full"
Requires-Dist: jupyter>=1.0.0; extra == "full"
Requires-Dist: matplotlib>=3.5.0; extra == "full"
Dynamic: author
Dynamic: home-page
Dynamic: requires-python
